lldb_typeinfo/__all__.pyi
lldb_typeinfo/__init__.py
lldb_typeinfo/error.pyi
lldb_typeinfo/frame.pyi
lldb_typeinfo/process.pyi
lldb_typeinfo/thread.pyi
lldb_typeinfo/value.pyi
lldb_typeinfo-2025.3.14.0.dist-info/METADATA
lldb_typeinfo-2025.3.14.0.dist-info/WHEEL
lldb_typeinfo-2025.3.14.0.dist-info/licenses/LICENSE
lldb_typeinfo-2025.3.14.0.dist-info/RECORD
