Metadata-Version: 2.4
Name: lldb-typeinfo
Version: 2025.3.14.0
Summary: Additional type information for lldb
Project-URL: Repository, https://github.com/soda92/lldb-typeinfo
License-File: LICENSE
Requires-Python: >=3.10
